bavera/__init__.py
bavera/cli.py
bavera/client.py
bavera/state.py
bavera/api/__init__.py
bavera/api/client.py
bavera/api/http.py
bavera/api/ratelimit.py
bavera/bot/__init__.py
bavera/bot/bot.py
bavera/bot/command.py
bavera/bot/parser.py
bavera/bot/plugin.py
bavera/bot/storage.py
bavera/gateway/__init__.py
bavera/gateway/client.py
bavera/gateway/events.py
bavera/gateway/ipc.py
bavera/gateway/packets.py
bavera/gateway/sharder.py
bavera/gateway/encoding/__init__.py
bavera/gateway/encoding/base.py
bavera/gateway/encoding/etf.py
bavera/gateway/encoding/json.py
bavera/types/__init__.py
bavera/types/base.py
bavera/types/channel.py
bavera/types/guild.py
bavera/types/invite.py
bavera/types/message.py
bavera/types/permissions.py
bavera/types/user.py
bavera/types/voice.py
bavera/types/webhook.py
bavera/util/__init__.py
bavera/util/backdoor.py
bavera/util/chains.py
bavera/util/config.py
bavera/util/functional.py
bavera/util/hashmap.py
bavera/util/limiter.py
bavera/util/logging.py
bavera/util/paginator.py
bavera/util/sanitize.py
bavera/util/serializer.py
bavera/util/snowflake.py
bavera/util/string.py
bavera/util/websocket.py
bavera/voice/__init__.py
bavera/voice/client.py
bavera/voice/opus.py
bavera/voice/packets.py
bavera/voice/playable.py
bavera/voice/player.py
bavera/voice/queue.py
bavera/voice/udp.py
examples/__init__.py
examples/basic_plugin.py
examples/music.py
tests/__init__.py
tests/imports.py
tests/state.py
tests/utils.py
tests/api/__init__.py
tests/api/client.py
tests/api/reason.py
tests/bot/__init__.py
tests/bot/bot.py
tests/bot/plugin.py
tests/gateway/__init__.py
tests/gateway/events.py
tests/types/__init__.py
tests/types/base.py
tests/types/channel.py
tests/types/embeds.py
tests/types/types.py
tests/util/__init__.py
tests/util/functional.py
tests/util/hashmap.py
tests/util/limiter.py
tests/voice/__init__.py
tests/voice/queue.py
bavera-0.14.dist-info/METADATA
bavera-0.14.dist-info/WHEEL
bavera-0.14.dist-info/top_level.txt
bavera-0.14.dist-info/RECORD
