Metadata-Version: 2.1
Name: bavera
Version: 0.14
Summary: A Pythonic Library For The Discord API
Home-page: https://github.com/bavera/bavera
Author: bavera
License: MIT
Platform: UNKNOWN
Classifier: Development Status :: 4 - Beta
Classifier: License :: OSI Approved :: MIT License
Classifier: Intended Audience :: Developers
Classifier: Natural Language :: English
Classifier: Operating System :: OS Independent
Classifier: Programming Language :: Python :: 3.8
Classifier: Programming Language :: Python :: 3.9
Classifier: Topic :: Internet
Classifier: Topic :: Software Development :: Libraries
Classifier: Topic :: Software Development :: Libraries :: Python Modules
Classifier: Topic :: Utilities
Requires-Dist: gevent (<21.9.0,>=21.3.0)
Requires-Dist: holster (<3,>=2.0.0)
Requires-Dist: requests (<3,>=2.25.1)
Requires-Dist: six (<2,>=1.13.0)
Requires-Dist: websocket-client (<1.2.2,>=1.0.0)
Provides-Extra: docs
Requires-Dist: biblio (==0.0.4) ; extra == 'docs'
Provides-Extra: http
Requires-Dist: flask (<2.0.2,>=1.0.0) ; extra == 'http'
Provides-Extra: music
Requires-Dist: youtube-dl (>=2021.6.6) ; extra == 'music'
Provides-Extra: sharding
Requires-Dist: gipc (<1.3.0,>=1.0.0) ; extra == 'sharding'
Provides-Extra: speed
Requires-Dist: earl-etf (==2.1.2) ; extra == 'speed'
Requires-Dist: ujson (==3.6.4) ; extra == 'speed'
Requires-Dist: wsaccel (<0.6.3,>=0.6.2) ; extra == 'speed'
Requires-Dist: aiodns (==3.0.0) ; extra == 'speed'
Provides-Extra: voice
Requires-Dist: pynacl (<1.4.0,>=1.3.0) ; extra == 'voice'
Provides-Extra: yaml
Requires-Dist: pyyaml (<6.0,>=3.12) ; extra == 'yaml'
